csp/__init__.py
csp/context_processors.py
csp/decorators.py
csp/middleware.py
csp/models.py
csp/utils.py
csp/contrib/__init__.py
csp/contrib/rate_limiting.py
csp/extensions/__init__.py
csp/templatetags/__init__.py
csp/templatetags/csp.py
csp/tests/__init__.py
csp/tests/environment.py
csp/tests/settings.py
csp/tests/test_context_processors.py
csp/tests/test_contrib.py
csp/tests/test_decorators.py
csp/tests/test_jinja_extension.py
csp/tests/test_middleware.py
csp/tests/test_templatetags.py
csp/tests/test_utils.py
csp/tests/utils.py
django_csp-3.8.dist-info/LICENSE
django_csp-3.8.dist-info/METADATA
django_csp-3.8.dist-info/WHEEL
django_csp-3.8.dist-info/top_level.txt
django_csp-3.8.dist-info/RECORD
